biblatex2qmd/__about__.py
biblatex2qmd/__init__.py
biblatex2qmd/bib_notes_parser.py
biblatex2qmd/bib_processor.py
biblatex2qmd-0.1.7.dist-info/METADATA
biblatex2qmd-0.1.7.dist-info/WHEEL
biblatex2qmd-0.1.7.dist-info/entry_points.txt
biblatex2qmd-0.1.7.dist-info/licenses/LICENSE
biblatex2qmd-0.1.7.dist-info/RECORD
