Metadata-Version: 2.3
Name: biblatex2qmd
Version: 0.1.7
Summary: BibLaTeX Processor is a Python package that processes BibLaTeX files, extracts information from each entry, creates individual Markdown files for each entry, and generates a combined corpus file.
Project-URL: Homepage, https://github.com/jan-ru/biblatex2qmd
Author-email: Jan-Ru Muller <janru.muller@edu.vlerick.com>
License: MIT License
License-File: LICENSE
Keywords: bib,latex,processor
Classifier: License :: OSI Approved :: MIT License
Classifier: Programming Language :: Python
Classifier: Programming Language :: Python :: 3
Requires-Python: >=3.7
Requires-Dist: bibtexparser
Requires-Dist: pytest
